[{"advisoryId":"WPSECADV/WF/bb74a917-2dfb-4229-a72a-9c3d1f9a6324/gamipress-youtube-integration","title":"GamiPress – Youtube integration <= 1.0.7 - Authenticated (Contributor+) Stored Cross-Site Scripting via Shortcode\n### Copyright 2012-2026 Defiant Inc.\nDefiant hereby grants you a perpetual, worldwide, non-exclusive, no-charge, royalty-free, irrevocable copyright license to reproduce, prepare derivative works of, publicly display, publicly perform, sublicense, and distribute this software vulnerability information. Any copy of the software vulnerability information you make for such purposes is authorized provided that you include a hyperlink to this vulnerability record and reproduce Defiant's copyright designation and this license in any such copy.\nhttps://www.wordfence.com/wordfence-intelligence-terms-and-conditions/","reportedAt":"2023-03-20 00:00:00","sources":[{"name":"Wordfence","remoteId":"bb74a917-2dfb-4229-a72a-9c3d1f9a6324"}],"link":"https://www.wordfence.com/threat-intel/vulnerabilities/id/bb74a917-2dfb-4229-a72a-9c3d1f9a6324?source=api-prod","affectedVersions":"<=1.0.7","severity":"medium"}]